{"duration":1260,"records":[{"duration":269,"stepId":"io.quarkus.arc.deployment.ArcProcessor#registerBeans","started":"14:53:12.966","dependents":[139,134,140,142,136,135,137,132,138,131,133],"id":130,"thread":"build-40"},{"duration":226,"stepId":"io.quarkus.arc.deployment.ArcProcessor#generateResources","started":"14:53:13.351","dependents":[160,156],"id":155,"thread":"build-7"},{"duration":161,"stepId":"io.quarkus.deployment.console.ConsoleProcessor#setupConsole","started":"14:53:12.348","dependents":[22,23,71,21],"id":20,"thread":"build-9"},{"duration":160,"stepId":"io.quarkus.deployment.steps.ConfigGenerationBuildStep#generateConfigClass","started":"14:53:12.683","dependents":[],"id":122,"thread":"build-4"},{"duration":149,"stepId":"io.quarkus.deployment.logging.LoggingResourceProcessor#setupLoggingRuntimeInit","started":"14:53:12.532","dependents":[117,52,154,122,121,162,38,155,123,33,139,26,28,160,42,116,150,27,32,39,29,25,43,51,102,81,156,157,152,134,159,65,83,114,113,112,61,70,158,153,151,161,140,141,60,75,145,142,148,146,118,136,135,59,99,90,66,107,67,130,137,129,69,31,128,72,79,147,132,84,35,89,149,120,71,57,101,30,80,143,144,138,131,133,126,127,110,125,68,86,85,124,87,119,73,74,105,108,106,109,96,64,97,36,76,34,82,37,88,91,95,92,93,103,94,100,98,41,111,50,63,40,115,44,45,48,46,47,53,62,49,78,77,104,56,58,54,55],"id":24,"thread":"build-5"},{"duration":125,"stepId":"io.quarkus.deployment.steps.ConfigGenerationBuildStep#generateMappings","started":"14:53:12.684","dependents":[150,149,138,131],"id":121,"thread":"build-10"},{"duration":112,"stepId":"io.quarkus.deployment.dev.testing.TestTracingProcessor#testConsoleCommand","started":"14:53:12.693","dependents":[120],"id":119,"thread":"build-7"},{"duration":103,"stepId":"io.quarkus.arc.deployment.BeanArchiveProcessor#build","started":"14:53:12.781","dependents":[139,137,129,128,127,125,124],"id":123,"thread":"build-40"},{"duration":91,"stepId":"io.quarkus.deployment.index.ApplicationArchiveBuildStep#build","started":"14:53:12.383","dependents":[123,160,19,113,146,118,23],"id":18,"thread":"build-4"},{"duration":75,"stepId":"io.quarkus.arc.deployment.SplitPackageProcessor#splitPackageDetection","started":"14:53:12.718","dependents":[155],"id":118,"thread":"build-21"},{"duration":73,"stepId":"io.quarkus.deployment.logging.LoggingResourceProcessor#logConsoleCommand","started":"14:53:12.702","dependents":[120],"id":104,"thread":"build-13"},{"duration":72,"stepId":"io.quarkus.arc.deployment.BuildTimeEnabledProcessor#findEnablementStereotypes","started":"14:53:12.695","dependents":[105,108,106,109],"id":97,"thread":"build-2"},{"duration":65,"stepId":"io.quarkus.arc.deployment.ArcProcessor#initialize","started":"14:53:12.900","dependents":[139,130],"id":129,"thread":"build-4"},{"duration":64,"stepId":"io.quarkus.arc.deployment.ArcProcessor#quarkusMain","started":"14:53:12.702","dependents":[123,107,129],"id":94,"thread":"build-44"},{"duration":52,"stepId":"io.quarkus.deployment.ide.IdeProcessor#detectRunningIdeProcesses","started":"14:53:12.345","dependents":[16],"id":15,"thread":"build-11"},{"duration":52,"stepId":"io.quarkus.arc.deployment.ArcProcessor#validate","started":"14:53:13.298","dependents":[155,160,150,148,146,147,149],"id":145,"thread":"build-4"},{"duration":51,"stepId":"io.quarkus.deployment.steps.BannerProcessor#recordBanner","started":"14:53:12.348","dependents":[162,24],"id":17,"thread":"build-5"},{"duration":47,"stepId":"io.quarkus.deployment.console.ConsoleProcessor#quitCommand","started":"14:53:12.702","dependents":[120],"id":77,"thread":"build-3"},{"duration":47,"stepId":"io.quarkus.deployment.console.ConsoleProcessor#helpCommand","started":"14:53:12.702","dependents":[120],"id":78,"thread":"build-12"},{"duration":43,"stepId":"io.quarkus.arc.deployment.ExecutorServiceProcessor#executorServiceBean","started":"14:53:12.716","dependents":[134,140,133],"id":84,"thread":"build-22"},{"duration":41,"stepId":"io.quarkus.deployment.logging.LoggingResourceProcessor#registerMetrics","started":"14:53:12.348","dependents":[162,24],"id":14,"thread":"build-10"},{"duration":39,"stepId":"io.quarkus.arc.deployment.ArcProcessor#registerSyntheticObservers","started":"14:53:13.254","dependents":[155,150,145,143,144],"id":142,"thread":"build-49"},{"duration":36,"stepId":"io.quarkus.deployment.steps.ConfigGenerationBuildStep#generateBuilders","started":"14:53:13.358","dependents":[],"id":154,"thread":"build-17"},{"duration":35,"stepId":"io.quarkus.deployment.steps.ConfigGenerationBuildStep#reportDeprecatedMappingProperties","started":"14:53:12.750","dependents":[162],"id":114,"thread":"build-17"},{"duration":34,"stepId":"io.quarkus.deployment.steps.ApplicationIndexBuildStep#build","started":"14:53:12.349","dependents":[136,18,129],"id":13,"thread":"build-3"},{"duration":33,"stepId":"io.quarkus.arc.deployment.StartupBuildSteps#addScope","started":"14:53:12.727","dependents":[128],"id":85,"thread":"build-8"},{"duration":31,"stepId":"io.quarkus.arc.deployment.ShutdownBuildSteps#shutdownAddScope","started":"14:53:12.730","dependents":[128],"id":86,"thread":"build-25"},{"duration":27,"stepId":"io.quarkus.deployment.steps.ThreadPoolSetup#createExecutor","started":"14:53:12.688","dependents":[162,70,84],"id":61,"thread":"build-6"},{"duration":24,"stepId":"io.quarkus.arc.deployment.LookupConditionsProcessor#findLookupConditionStereotypes","started":"14:53:12.743","dependents":[125],"id":96,"thread":"build-35"},{"duration":22,"stepId":"io.quarkus.arc.deployment.ArcProcessor#setupExecutor","started":"14:53:12.716","dependents":[162],"id":70,"thread":"build-19"},{"duration":20,"stepId":"io.quarkus.deployment.dev.HotDeploymentWatchedFileBuildStep#setupWatchedFileHotDeployment","started":"14:53:12.748","dependents":[161],"id":101,"thread":"build-33"},{"duration":20,"stepId":"io.quarkus.deployment.steps.ConfigGenerationBuildStep#checkForBuildTimeConfigChange","started":"14:53:12.703","dependents":[162],"id":65,"thread":"build-8"},{"duration":19,"stepId":"io.quarkus.deployment.steps.ConfigGenerationBuildStep#unknownConfigFiles","started":"14:53:12.766","dependents":[162],"id":113,"thread":"build-18"},{"duration":19,"stepId":"io.quarkus.deployment.dev.testing.TestTracingProcessor#startTesting","started":"14:53:12.509","dependents":[24,161],"id":22,"thread":"build-5"},{"duration":18,"stepId":"io.quarkus.arc.deployment.ArcProcessor#buildCompatibleExtensions","started":"14:53:12.701","dependents":[123,129],"id":63,"thread":"build-30"},{"duration":18,"stepId":"io.quarkus.deployment.steps.ConfigGenerationBuildStep#buildTimeRunTimeConfig","started":"14:53:12.683","dependents":[154],"id":52,"thread":"build-5"},{"duration":18,"stepId":"io.quarkus.deployment.steps.CapabilityAggregationStep#provideCapabilities","started":"14:53:12.704","dependents":[68],"id":64,"thread":"build-5"},{"duration":17,"stepId":"io.quarkus.deployment.steps.MainClassBuildStep#build","started":"14:53:13.584","dependents":[],"id":162,"thread":"build-23"},{"duration":17,"stepId":"io.quarkus.arc.deployment.ConfigStaticInitBuildSteps#transformConfigProducer","started":"14:53:12.702","dependents":[129],"id":62,"thread":"build-9"},{"duration":16,"stepId":"io.quarkus.deployment.steps.MainClassBuildStep#mainClassBuildStep","started":"14:53:12.684","dependents":[160],"id":38,"thread":"build-11"},{"duration":16,"stepId":"io.quarkus.deployment.steps.NativeImageConfigBuildStep#build","started":"14:53:12.754","dependents":[162],"id":102,"thread":"build-12"},{"duration":15,"stepId":"io.quarkus.deployment.logging.LoggingResourceProcessor#setupStackTraceFormatter","started":"14:53:12.516","dependents":[24],"id":23,"thread":"build-9"},{"duration":14,"stepId":"io.quarkus.arc.deployment.devui.ArcDevUIProcessor#createJsonRPCService","started":"14:53:12.775","dependents":[116],"id":115,"thread":"build-49"},{"duration":13,"stepId":"io.quarkus.deployment.steps.ProfileBuildStep#defaultProfile","started":"14:53:12.687","dependents":[154],"id":39,"thread":"build-12"},{"duration":13,"stepId":"io.quarkus.arc.deployment.SyntheticBeansProcessor#initRuntime","started":"14:53:13.239","dependents":[162,161,141,142],"id":140,"thread":"build-40"},{"duration":12,"stepId":"io.quarkus.arc.deployment.AutoAddScopeProcessor#annotationTransformer","started":"14:53:12.887","dependents":[150,145,129],"id":128,"thread":"build-40"},{"duration":12,"stepId":"io.quarkus.arc.deployment.staticmethods.InterceptedStaticMethodsProcessor#collectInterceptedStaticMethods","started":"14:53:13.235","dependents":[139,150,159,145],"id":137,"thread":"build-10"},{"duration":12,"stepId":"io.quarkus.arc.deployment.ConfigBuildStep#registerConfigMappingsBean","started":"14:53:13.235","dependents":[142],"id":138,"thread":"build-49"},{"duration":11,"stepId":"io.quarkus.arc.deployment.BuildTimeEnabledProcessor#unlessBuildProperty","started":"14:53:12.769","dependents":[110],"id":109,"thread":"build-42"},{"duration":11,"stepId":"io.quarkus.deployment.steps.CompiledJavaVersionBuildStep#compiledJavaVersion","started":"14:53:12.750","dependents":[89],"id":87,"thread":"build-32"},{"duration":10,"stepId":"io.quarkus.arc.deployment.ConfigBuildStep#generateConfigProperties","started":"14:53:12.684","dependents":[150,149,138,131],"id":33,"thread":"build-3"},{"duration":9,"stepId":"io.quarkus.deployment.steps.DevServicesConfigBuildStep#setup","started":"14:53:12.685","dependents":[154,161],"id":32,"thread":"build-2"},{"duration":9,"stepId":"io.quarkus.deployment.steps.ShutdownListenerBuildStep#setupShutdown","started":"14:53:12.773","dependents":[162],"id":112,"thread":"build-47"},{"duration":8,"stepId":"io.quarkus.arc.deployment.BuildTimeEnabledProcessor#unlessBuildProfile","started":"14:53:12.768","dependents":[110],"id":106,"thread":"build-44"},{"duration":8,"stepId":"io.quarkus.arc.deployment.BuildTimeEnabledProcessor#ifBuildProfile","started":"14:53:12.768","dependents":[110],"id":105,"thread":"build-35"},{"duration":7,"stepId":"io.quarkus.deployment.dev.io.NioThreadPoolDevModeProcessor#setupTCCL","started":"14:53:12.685","dependents":[162],"id":29,"thread":"build-7"},{"duration":7,"stepId":"io.quarkus.arc.deployment.ConfigBuildStep#validateConfigMappingsInjectionPoints","started":"14:53:13.350","dependents":[154],"id":150,"thread":"build-40"},{"duration":7,"stepId":"io.quarkus.arc.deployment.BuildTimeEnabledProcessor#ifBuildProperty","started":"14:53:12.771","dependents":[110],"id":108,"thread":"build-40"},{"duration":7,"stepId":"io.quarkus.arc.deployment.ConfigBuildStep#validateStaticInitConfigProperty","started":"14:53:13.351","dependents":[162],"id":152,"thread":"build-10"},{"duration":7,"stepId":"io.quarkus.arc.deployment.ConfigBuildStep#validateRuntimeConfigProperty","started":"14:53:13.351","dependents":[162],"id":151,"thread":"build-4"},{"duration":7,"stepId":"io.quarkus.arc.deployment.WrongAnnotationUsageProcessor#detect","started":"14:53:13.235","dependents":[155],"id":136,"thread":"build-4"},{"duration":6,"stepId":"io.quarkus.deployment.console.ConsoleProcessor#setupExceptionHandler","started":"14:53:12.509","dependents":[23],"id":21,"thread":"build-4"},{"duration":6,"stepId":"io.quarkus.deployment.steps.PreloadClassesBuildStep#preInit","started":"14:53:12.750","dependents":[162],"id":81,"thread":"build-15"},{"duration":6,"stepId":"io.quarkus.deployment.pkg.steps.FileSystemResourcesBuildStep#notNormalMode","started":"14:53:12.684","dependents":[],"id":28,"thread":"build-8"},{"duration":6,"stepId":"io.quarkus.deployment.steps.CombinedIndexBuildStep#build","started":"14:53:12.475","dependents":[117,154,121,38,33,24,99,129,69,30,119,105,108,106,109,96,97],"id":19,"thread":"build-5"},{"duration":6,"stepId":"io.quarkus.arc.deployment.devui.ArcDevUIProcessor#registerMonitoringComponents","started":"14:53:12.770","dependents":[123,129],"id":107,"thread":"build-23"},{"duration":6,"stepId":"io.quarkus.deployment.console.ConsoleProcessor#missingDevUIMessageHandler","started":"14:53:12.731","dependents":[161],"id":71,"thread":"build-26"},{"duration":5,"stepId":"io.quarkus.deployment.steps.CapabilityAggregationStep#aggregateCapabilities","started":"14:53:12.723","dependents":[129,71],"id":68,"thread":"build-30"},{"duration":5,"stepId":"io.quarkus.deployment.steps.ConfigGenerationBuildStep#setupConfigOverride","started":"14:53:12.695","dependents":[],"id":36,"thread":"build-8"},{"duration":5,"stepId":"io.quarkus.arc.deployment.AutoProducerMethodsProcessor#annotationTransformer","started":"14:53:12.884","dependents":[129],"id":127,"thread":"build-4"},{"duration":5,"stepId":"io.quarkus.arc.deployment.ArcProcessor#feature","started":"14:53:12.765","dependents":[162],"id":103,"thread":"build-43"},{"duration":5,"stepId":"io.quarkus.arc.deployment.ReflectiveBeanClassesProcessor#implicitReflectiveBeanClasses","started":"14:53:13.235","dependents":[155],"id":135,"thread":"build-7"},{"duration":5,"stepId":"io.quarkus.deployment.steps.ConfigGenerationBuildStep#watchConfigFiles","started":"14:53:12.702","dependents":[101],"id":58,"thread":"build-14"},{"duration":5,"stepId":"io.quarkus.arc.deployment.ArcProcessor#quarkusApplication","started":"14:53:12.763","dependents":[123,129],"id":99,"thread":"build-23"},{"duration":5,"stepId":"io.quarkus.deployment.steps.ClassTransformingBuildStep#handleClassTransformation","started":"14:53:13.579","dependents":[],"id":160,"thread":"build-23"},{"duration":5,"stepId":"io.quarkus.deployment.steps.DevModeBuildStep#watchChanges","started":"14:53:12.741","dependents":[101],"id":74,"thread":"build-34"},{"duration":5,"stepId":"io.quarkus.deployment.steps.BlockingOperationControlBuildStep#blockingOP","started":"14:53:12.696","dependents":[162],"id":43,"thread":"build-13"},{"duration":4,"stepId":"io.quarkus.arc.deployment.StartupBuildSteps#registerStartupObservers","started":"14:53:13.294","dependents":[145],"id":144,"thread":"build-40"},{"duration":4,"stepId":"io.quarkus.arc.deployment.ValueRegistryProcessor#valueRegistry","started":"14:53:12.762","dependents":[162,134,140,133],"id":95,"thread":"build-40"},{"duration":4,"stepId":"io.quarkus.arc.deployment.ConfigBuildStep#registerConfigClasses","started":"14:53:13.354","dependents":[162,161],"id":153,"thread":"build-49"},{"duration":4,"stepId":"io.quarkus.deployment.logging.LoggingResourceProcessor#setMinLevelForInitialConfigurator","started":"14:53:12.706","dependents":[162],"id":60,"thread":"build-19"},{"duration":4,"stepId":"io.quarkus.arc.deployment.init.InitializationTaskProcessor#startApplicationInitializer","started":"14:53:13.254","dependents":[162],"id":141,"thread":"build-4"},{"duration":3,"stepId":"io.quarkus.arc.deployment.ConfigBuildStep#validateConfigPropertiesInjectionPoints","started":"14:53:13.350","dependents":[153],"id":149,"thread":"build-17"},{"duration":3,"stepId":"io.quarkus.arc.deployment.ConfigBuildStep#additionalBeans","started":"14:53:12.778","dependents":[123,129],"id":111,"thread":"build-48"},{"duration":3,"stepId":"io.quarkus.deployment.recording.substitutions.AdditionalSubstitutionsBuildStep#additionalSubstitutions","started":"14:53:12.697","dependents":[162],"id":37,"thread":"build-3"},{"duration":3,"stepId":"io.quarkus.deployment.execannotations.ExecutionModelAnnotationsProcessor#devuiJsonRpcServices","started":"14:53:12.744","dependents":[117],"id":76,"thread":"build-36"},{"duration":3,"stepId":"io.quarkus.arc.deployment.HotDeploymentConfigBuildStep#startup","started":"14:53:12.702","dependents":[57],"id":56,"thread":"build-11"},{"duration":3,"stepId":"io.quarkus.deployment.logging.LoggingResourceProcessor#setUpDefaultLogCleanupFilters","started":"14:53:12.684","dependents":[154],"id":27,"thread":"build-6"},{"duration":3,"stepId":"io.quarkus.arc.deployment.ShutdownBuildSteps#registerShutdownObservers","started":"14:53:13.293","dependents":[145],"id":143,"thread":"build-4"},{"duration":3,"stepId":"io.quarkus.arc.deployment.ConfigBuildStep#registerConfigPropertiesBean","started":"14:53:13.235","dependents":[142],"id":131,"thread":"build-17"},{"duration":3,"stepId":"io.quarkus.deployment.ExtensionLoader#config","started":"14:53:12.344","dependents":[117,52,154,122,121,162,38,155,123,33,160,150,25,102,156,14,24,17,65,114,112,61,161,141,60,75,118,136,18,107,129,12,10,31,72,79,22,23,35,89,149,143,13,11,126,127,86,20,16,73,74],"id":8,"thread":"build-3"},{"duration":3,"stepId":"io.quarkus.arc.deployment.ConfigBuildStep#registerCustomConfigBeanTypes","started":"14:53:13.235","dependents":[134,140,133],"id":132,"thread":"build-21"},{"duration":2,"stepId":"io.quarkus.deployment.console.ConsoleProcessor#installCliCommands","started":"14:53:12.807","dependents":[161],"id":120,"thread":"build-21"},{"duration":2,"stepId":"io.quarkus.deployment.logging.LoggingResourceProcessor#setupLogFilters","started":"14:53:12.345","dependents":[27,24],"id":5,"thread":"build-7"},{"duration":2,"stepId":"io.quarkus.deployment.steps.RuntimeConfigSetupBuildStep#setupRuntimeConfig","started":"14:53:12.344","dependents":[162,24,17,112,61,161,141],"id":3,"thread":"build-2"},{"duration":2,"stepId":"io.quarkus.arc.deployment.ArcProcessor#initializeContainer","started":"14:53:13.579","dependents":[162,157],"id":156,"thread":"build-17"},{"duration":2,"stepId":"io.quarkus.deployment.steps.AdditionalClassLoaderResourcesBuildStep#appendAdditionalClassloaderResources","started":"14:53:12.344","dependents":[19],"id":7,"thread":"build-5"},{"duration":2,"stepId":"io.quarkus.deployment.logging.LoggingResourceProcessor#setupLoggingStaticInit","started":"14:53:12.682","dependents":[117,52,154,122,121,162,38,155,123,33,139,26,28,160,42,116,150,27,32,39,29,43,51,102,81,156,157,152,134,159,65,83,114,113,112,61,70,158,153,151,161,140,141,60,75,145,142,148,146,118,136,135,59,99,90,66,107,67,130,137,129,69,31,128,72,79,147,132,84,35,89,149,120,71,57,101,30,80,143,144,138,131,133,126,127,110,125,68,86,85,124,87,119,73,74,105,108,106,109,96,64,97,36,76,34,82,37,88,91,95,92,93,103,94,100,98,41,111,50,63,40,115,44,45,48,46,47,53,62,49,78,77,104,56,58,54,55],"id":25,"thread":"build-9"},{"duration":2,"stepId":"io.quarkus.arc.deployment.ValueRegistryProcessor#runtimeInfo","started":"14:53:12.760","dependents":[162,134,140,133],"id":91,"thread":"build-39"},{"duration":2,"stepId":"io.quarkus.deployment.ide.IdeProcessor#detectIdeFiles","started":"14:53:12.345","dependents":[16],"id":9,"thread":"build-10"},{"duration":2,"stepId":"io.quarkus.arc.deployment.ShutdownBuildSteps#unremovableBeans","started":"14:53:12.737","dependents":[150,145],"id":72,"thread":"build-28"},{"duration":2,"stepId":"io.quarkus.deployment.steps.ClassPathSystemPropBuildStep#set","started":"14:53:12.700","dependents":[162],"id":51,"thread":"build-14"},{"duration":2,"stepId":"io.quarkus.deployment.logging.LoggingResourceProcessor#setUpDefaultLevels","started":"14:53:12.344","dependents":[154,24],"id":6,"thread":"build-4"},{"duration":2,"stepId":"io.quarkus.deployment.dev.testing.TestTracingProcessor#handle","started":"14:53:12.345","dependents":[27,24],"id":4,"thread":"build-6"},{"duration":1,"stepId":"io.quarkus.deployment.steps.ValueRegistryProcessor#discoverRuntimeInfos","started":"14:53:12.760","dependents":[162],"id":88,"thread":"build-38"},{"duration":1,"stepId":"io.quarkus.deployment.pkg.steps.JarResultBuildStep#outputTarget","started":"14:53:12.348","dependents":[28,23,89],"id":12,"thread":"build-4"},{"duration":1,"stepId":"io.quarkus.arc.deployment.ArcProcessor#launchMode","started":"14:53:12.767","dependents":[123,129],"id":98,"thread":"build-46"},{"duration":1,"stepId":"io.quarkus.arc.deployment.SyntheticBeansProcessor#initStatic","started":"14:53:13.239","dependents":[162,142],"id":134,"thread":"build-17"},{"duration":1,"stepId":"io.quarkus.arc.deployment.ArcProcessor#loggerProducer","started":"14:53:12.700","dependents":[123,129],"id":41,"thread":"build-8"},{"duration":1,"stepId":"io.quarkus.deployment.logging.LoggingResourceProcessor#closeBuildTimeLogging","started":"14:53:12.752","dependents":[161],"id":80,"thread":"build-31"},{"duration":1,"stepId":"io.quarkus.deployment.SslProcessor#setupNativeSsl","started":"14:53:12.751","dependents":[102],"id":79,"thread":"build-29"},{"duration":1,"stepId":"io.quarkus.deployment.steps.CurateOutcomeBuildStep#removeResources","started":"14:53:12.692","dependents":[160],"id":31,"thread":"build-8"},{"duration":1,"stepId":"io.quarkus.arc.deployment.LookupConditionsProcessor#suppressConditionsGenerators","started":"14:53:12.884","dependents":[129],"id":125,"thread":"build-10"},{"duration":1,"stepId":"io.quarkus.deployment.ide.IdeProcessor#effectiveIde","started":"14:53:12.397","dependents":[23,21],"id":16,"thread":"build-10"},{"duration":1,"stepId":"io.quarkus.deployment.pkg.steps.JvmStartupOptimizerArchiveBuildStep#requested","started":"14:53:12.762","dependents":[158],"id":89,"thread":"build-25"},{"duration":1,"stepId":"io.quarkus.deployment.index.ApplicationArchiveBuildStep#addConfiguredIndexedDependencies","started":"14:53:12.348","dependents":[18],"id":11,"thread":"build-7"},{"duration":1,"stepId":"io.quarkus.arc.deployment.ArcProcessor#notifyBeanContainerListeners","started":"14:53:13.581","dependents":[162,158],"id":157,"thread":"build-49"},{"duration":1,"stepId":"io.quarkus.arc.deployment.ArcProcessor#marker","started":"14:53:12.345","dependents":[18],"id":2,"thread":"build-8"},{"duration":1,"stepId":"io.quarkus.deployment.steps.ConfigGenerationBuildStep#runtimeOverrideConfig","started":"14:53:12.754","dependents":[154],"id":82,"thread":"build-37"},{"duration":1,"stepId":"io.quarkus.arc.deployment.devui.JsonRpcMethodsProcessor#jsonRpcMethods","started":"14:53:12.789","dependents":[117],"id":116,"thread":"build-17"},{"duration":1,"stepId":"io.quarkus.arc.deployment.AutoInjectFieldProcessor#annotationTransformer","started":"14:53:12.887","dependents":[129],"id":126,"thread":"build-7"},{"duration":1,"stepId":"io.quarkus.arc.deployment.AutoInjectFieldProcessor#autoInjectQualifiers","started":"14:53:12.884","dependents":[128,126],"id":124,"thread":"build-21"},{"duration":1,"stepId":"io.quarkus.deployment.steps.ApplicationInfoBuildStep#create","started":"14:53:12.745","dependents":[162],"id":75,"thread":"build-20"},{"duration":1,"stepId":"io.quarkus.deployment.steps.CurateOutcomeBuildStep#curateOutcome","started":"14:53:12.348","dependents":[160,51,18,31,23,13,68,87,64],"id":10,"thread":"build-8"},{"duration":1,"stepId":"io.quarkus.deployment.dev.testing.TestTracingProcessor#sharedStateListener","started":"14:53:12.345","dependents":[22],"id":1,"thread":"build-9"},{"duration":1,"stepId":"io.quarkus.arc.deployment.ConfigStaticInitBuildSteps#registerBeans","started":"14:53:12.701","dependents":[123,129],"id":50,"thread":"build-11"},{"duration":0,"stepId":"io.quarkus.deployment.ForkJoinPoolProcessor#setProperty","started":"14:53:12.764","dependents":[162],"id":92,"thread":"build-41"},{"duration":0,"stepId":"io.quarkus.deployment.steps.ConfigGenerationBuildStep#releaseConfigOnShutdown","started":"14:53:12.757","dependents":[162],"id":83,"thread":"build-16"},{"duration":0,"stepId":"io.quarkus.deployment.steps.ConfigGenerationBuildStep#suppressNonRuntimeConfigChanged","started":"14:53:12.702","dependents":[65],"id":47,"thread":"build-12"},{"duration":0,"stepId":"io.quarkus.deployment.pkg.steps.NativeImageBuildStep#ignoreBuildPropertyChanges","started":"14:53:12.702","dependents":[65],"id":46,"thread":"build-9"},{"duration":0,"stepId":"io.quarkus.arc.deployment.ObserverValidationProcessor#validateApplicationObserver","started":"14:53:13.350","dependents":[155],"id":146,"thread":"build-10"},{"duration":0,"stepId":"io.quarkus.arc.deployment.LoggingBeanSupportProcessor#discoveredComponents","started":"14:53:12.768","dependents":[123,107,129],"id":100,"thread":"build-45"},{"duration":0,"stepId":"io.quarkus.deployment.JBossThreadsProcessor#allowClearThreadLocals","started":"14:53:12.701","dependents":[42],"id":40,"thread":"build-3"},{"duration":0,"stepId":"io.quarkus.arc.deployment.UnremovableAnnotationsProcessor#unremovableBeans","started":"14:53:12.701","dependents":[150,145],"id":48,"thread":"build-3"},{"duration":0,"stepId":"io.quarkus.deployment.steps.JvmRequirementsBuildStep#resolveJVMRequirements","started":"14:53:12.701","dependents":[],"id":42,"thread":"build-12"},{"duration":0,"stepId":"io.quarkus.arc.deployment.SyntheticBeansProcessor#initRegular","started":"14:53:13.239","dependents":[142],"id":133,"thread":"build-18"},{"duration":0,"stepId":"io.quarkus.arc.deployment.HotDeploymentConfigBuildStep#configFile","started":"14:53:12.703","dependents":[101],"id":54,"thread":"build-8"},{"duration":0,"stepId":"io.quarkus.arc.deployment.ArcProcessor#registerPreShutdownListener","started":"14:53:12.700","dependents":[112],"id":35,"thread":"build-30"},{"duration":0,"stepId":"io.quarkus.deployment.logging.LoggingResourceProcessor#setProperties","started":"14:53:12.764","dependents":[162],"id":93,"thread":"build-42"},{"duration":0,"stepId":"io.quarkus.arc.deployment.ConfigBuildStep#vetoMPConfigProperties","started":"14:53:12.702","dependents":[129],"id":53,"thread":"build-8"},{"duration":0,"stepId":"io.quarkus.deployment.dev.RecompilationDependenciesProcessor#consolidateRecompilationDependencies","started":"14:53:12.692","dependents":[161],"id":30,"thread":"build-7"},{"duration":0,"stepId":"io.quarkus.arc.deployment.TestsAsBeansProcessor#testAnnotations","started":"14:53:12.709","dependents":[123,107,129],"id":59,"thread":"build-22"},{"duration":0,"stepId":"io.quarkus.arc.deployment.ArcProcessor#unremovableAsyncObserverExceptionHandlers","started":"14:53:12.701","dependents":[150,145],"id":44,"thread":"build-12"},{"duration":0,"stepId":"io.quarkus.arc.deployment.staticmethods.InterceptedStaticMethodsProcessor#callInitializer","started":"14:53:13.583","dependents":[162],"id":159,"thread":"build-49"},{"duration":0,"stepId":"io.quarkus.arc.deployment.ConfigBuildStep#configPropertyInjectionPoints","started":"14:53:13.350","dependents":[152,151],"id":147,"thread":"build-7"},{"duration":0,"stepId":"io.quarkus.arc.deployment.LifecycleEventsBuildStep#startupEvent","started":"14:53:13.583","dependents":[162],"id":161,"thread":"build-4"},{"duration":0,"stepId":"io.quarkus.arc.deployment.CommandLineArgumentsProcessor#commandLineArgs","started":"14:53:12.763","dependents":[123,134,140,129,133],"id":90,"thread":"build-24"},{"duration":0,"stepId":"io.quarkus.arc.deployment.ArcProcessor#validateAsyncObserverExceptionHandlers","started":"14:53:13.350","dependents":[155],"id":148,"thread":"build-49"},{"duration":0,"stepId":"io.quarkus.arc.deployment.TestsAsBeansProcessor#testClassBeans","started":"14:53:12.725","dependents":[123,129],"id":66,"thread":"build-25"},{"duration":0,"stepId":"io.quarkus.deployment.execannotations.ExecutionModelAnnotationsProcessor#check","started":"14:53:12.792","dependents":[],"id":117,"thread":"build-49"},{"duration":0,"stepId":"io.quarkus.arc.deployment.StartupBuildSteps#unremovableBeans","started":"14:53:12.702","dependents":[150,145],"id":45,"thread":"build-8"},{"duration":0,"stepId":"io.quarkus.deployment.steps.PreloadClassesBuildStep#registerPreInitClasses","started":"14:53:12.684","dependents":[],"id":26,"thread":"build-7"},{"duration":0,"stepId":"io.quarkus.arc.deployment.staticmethods.InterceptedStaticMethodsProcessor#processInterceptedStaticMethods","started":"14:53:13.249","dependents":[160],"id":139,"thread":"build-4"},{"duration":0,"stepId":"io.quarkus.deployment.dev.IsolatedDevModeMain$AddApplicationClassPredicateBuildStep$1@60c2ffe4","started":"14:53:12.702","dependents":[129],"id":49,"thread":"build-13"},{"duration":0,"stepId":"io.quarkus.deployment.ExtensionLoader#booleanSupplierFactory","started":"14:53:12.703","dependents":[64],"id":55,"thread":"build-5"},{"duration":0,"stepId":"io.quarkus.deployment.steps.BannerProcessor#watchBannerChanges","started":"14:53:12.740","dependents":[101],"id":73,"thread":"build-33"},{"duration":0,"stepId":"io.quarkus.arc.deployment.ArcProcessor#exposeCustomScopeNames","started":"14:53:12.726","dependents":[123,136,107,129,128,127,86,85],"id":67,"thread":"build-26"},{"duration":0,"stepId":"io.quarkus.deployment.logging.LoggingResourceProcessor#setUpDarkeningDefault","started":"14:53:12.696","dependents":[154],"id":34,"thread":"build-3"},{"duration":0,"stepId":"io.quarkus.arc.deployment.ArcProcessor#signalBeanContainerReady","started":"14:53:13.583","dependents":[162,159,161],"id":158,"thread":"build-17"},{"duration":0,"stepId":"io.quarkus.deployment.dev.ConfigureDisableInstrumentationBuildStep#configure","started":"14:53:12.706","dependents":[161],"id":57,"thread":"build-11"},{"duration":0,"stepId":"io.quarkus.deployment.logging.LoggingWithPanacheProcessor#process","started":"14:53:12.734","dependents":[160],"id":69,"thread":"build-27"},{"duration":0,"stepId":"io.quarkus.arc.deployment.BuildTimeEnabledProcessor#conditionTransformer","started":"14:53:12.780","dependents":[129],"id":110,"thread":"build-40"}],"started":"2026-04-22T14:53:12.342","items":[{"count":135,"class":"io.quarkus.deployment.builditem.nativeimage.ReflectiveClassBuildItem"},{"count":84,"class":"io.quarkus.deployment.builditem.GeneratedClassBuildItem"},{"count":54,"class":"io.quarkus.deployment.builditem.nativeimage.ReflectiveMethodBuildItem"},{"count":26,"class":"io.quarkus.hibernate.validator.spi.AdditionalConstrainedClassBuildItem"},{"count":18,"class":"io.quarkus.deployment.builditem.MainBytecodeRecorderBuildItem"},{"count":16,"class":"io.quarkus.arc.deployment.BeanRegistrationPhaseBuildItem$BeanConfiguratorBuildItem"},{"count":16,"class":"io.quarkus.deployment.builditem.ConfigClassBuildItem"},{"count":11,"class":"io.quarkus.deployment.builditem.StaticBytecodeRecorderBuildItem"},{"count":10,"class":"io.quarkus.deployment.builditem.SuppressNonRuntimeConfigChangedWarningBuildItem"},{"count":10,"class":"io.quarkus.deployment.builditem.HotDeploymentWatchedFileBuildItem"},{"count":7,"class":"io.quarkus.arc.deployment.AdditionalBeanBuildItem"},{"count":7,"class":"io.quarkus.deployment.builditem.BytecodeTransformerBuildItem"},{"count":6,"class":"io.quarkus.arc.deployment.AnnotationsTransformerBuildItem"},{"count":4,"class":"io.quarkus.arc.deployment.UnremovableBeanBuildItem"},{"count":4,"class":"io.quarkus.deployment.builditem.SystemPropertyBuildItem"},{"count":4,"class":"io.quarkus.deployment.builditem.RunTimeConfigurationDefaultBuildItem"},{"count":4,"class":"io.quarkus.deployment.builditem.ConsoleCommandBuildItem"},{"count":3,"class":"io.quarkus.arc.deployment.SyntheticBeanBuildItem"},{"count":3,"class":"io.quarkus.deployment.builditem.AdditionalApplicationArchiveMarkerBuildItem"},{"count":3,"class":"io.quarkus.deployment.builditem.BytecodeRecorderObjectLoaderBuildItem"},{"count":2,"class":"io.quarkus.deployment.builditem.RunTimeConfigBuilderBuildItem"},{"count":2,"class":"io.quarkus.deployment.dev.testing.TestListenerBuildItem"},{"count":2,"class":"io.quarkus.deployment.builditem.ObjectSubstitutionBuildItem"},{"count":2,"class":"io.quarkus.deployment.logging.LogCleanupFilterBuildItem"},{"count":2,"class":"io.quarkus.arc.deployment.AutoAddScopeBuildItem"},{"count":2,"class":"io.quarkus.deployment.execannotations.ExecutionModelAnnotationsAllowedBuildItem"},{"count":2,"class":"io.quarkus.deployment.builditem.StaticInitConfigBuilderBuildItem"},{"count":2,"class":"io.quarkus.deployment.builditem.nativeimage.NativeImageSystemPropertyBuildItem"},{"count":2,"class":"io.quarkus.arc.deployment.BeanDefiningAnnotationBuildItem"},{"count":1,"class":"io.quarkus.arc.deployment.PreBeanContainerBuildItem"},{"count":1,"class":"io.quarkus.deployment.builditem.TransformedClassesBuildItem"},{"count":1,"class":"io.quarkus.deployment.builditem.ApplicationIndexBuildItem"},{"count":1,"class":"io.quarkus.deployment.console.ConsoleInstalledBuildItem"},{"count":1,"class":"io.quarkus.deployment.builditem.CombinedIndexBuildItem"},{"count":1,"class":"io.quarkus.deployment.Capabilities"},{"count":1,"class":"io.quarkus.arc.deployment.BeanDiscoveryFinishedBuildItem"},{"count":1,"class":"io.quarkus.deployment.jvm.ResolvedJVMRequirements"},{"count":1,"class":"io.quarkus.deployment.builditem.FeatureBuildItem"},{"count":1,"class":"io.quarkus.deployment.logging.LoggingSetupBuildItem"},{"count":1,"class":"io.quarkus.deployment.builditem.RunTimeConfigurationProxyBuildItem"},{"count":1,"class":"io.quarkus.deployment.builditem.ExecutorBuildItem"},{"count":1,"class":"io.quarkus.arc.deployment.SynthesisFinishedBuildItem"},{"count":1,"class":"io.quarkus.deployment.builditem.ShutdownListenerBuildItem"},{"count":1,"class":"io.quarkus.deployment.builditem.CapabilityBuildItem"},{"count":1,"class":"io.quarkus.arc.deployment.ArcContainerBuildItem"},{"count":1,"class":"io.quarkus.arc.deployment.BeanRegistrationPhaseBuildItem"},{"count":1,"class":"io.quarkus.arc.deployment.ObserverRegistrationPhaseBuildItem"},{"count":1,"class":"io.quarkus.deployment.builditem.ApplicationClassNameBuildItem"},{"count":1,"class":"io.quarkus.deployment.dev.DisableInstrumentationForIndexPredicateBuildItem"},{"count":1,"class":"io.quarkus.deployment.logging.LoggingDecorateBuildItem"},{"count":1,"class":"io.quarkus.arc.deployment.BuildCompatibleExtensionsBuildItem"},{"count":1,"class":"io.quarkus.arc.deployment.BeanContainerBuildItem"},{"count":1,"class":"io.quarkus.deployment.builditem.ModuleOpenBuildItem"},{"count":1,"class":"io.quarkus.deployment.ide.EffectiveIdeBuildItem"},{"count":1,"class":"io.quarkus.arc.deployment.InterceptorResolverBuildItem"},{"count":1,"class":"io.quarkus.deployment.dev.ExceptionNotificationBuildItem"},{"count":1,"class":"io.quarkus.deployment.pkg.builditem.CurateOutcomeBuildItem"},{"count":1,"class":"io.quarkus.deployment.pkg.builditem.CompiledJavaVersionBuildItem"},{"count":1,"class":"io.quarkus.deployment.builditem.ConfigurationBuildItem"},{"count":1,"class":"io.quarkus.deployment.steps.CapabilityAggregationStep$CapabilitiesConfiguredInDescriptorsBuildItem"},{"count":1,"class":"io.quarkus.arc.deployment.LookupConditionsStereotypesBuildItem"},{"count":1,"class":"io.quarkus.deployment.builditem.ApplicationStartBuildItem"},{"count":1,"class":"io.quarkus.devui.spi.JsonRPCProvidersBuildItem"},{"count":1,"class":"io.quarkus.deployment.builditem.ApplicationClassPredicateBuildItem"},{"count":1,"class":"io.quarkus.arc.deployment.ValidationPhaseBuildItem"},{"count":1,"class":"io.quarkus.arc.deployment.BeanArchiveIndexBuildItem"},{"count":1,"class":"io.quarkus.deployment.builditem.ServiceStartBuildItem"},{"count":1,"class":"io.quarkus.deployment.builditem.LogCategoryMinLevelDefaultsBuildItem"},{"count":1,"class":"io.quarkus.deployment.builditem.ConsoleFormatterBannerBuildItem"},{"count":1,"class":"io.quarkus.arc.deployment.SuppressConditionGeneratorBuildItem"},{"count":1,"class":"io.quarkus.arc.deployment.BuildTimeEnabledStereotypesBuildItem"},{"count":1,"class":"io.quarkus.deployment.builditem.GeneratedResourceBuildItem"},{"count":1,"class":"io.quarkus.arc.deployment.ContextRegistrationPhaseBuildItem"},{"count":1,"class":"io.quarkus.deployment.builditem.ApplicationArchivesBuildItem"},{"count":1,"class":"io.quarkus.deployment.BooleanSupplierFactoryBuildItem"},{"count":1,"class":"io.quarkus.arc.deployment.CustomScopeAnnotationsBuildItem"},{"count":1,"class":"io.quarkus.arc.deployment.InvokerFactoryBuildItem"},{"count":1,"class":"io.quarkus.deployment.builditem.SslNativeConfigBuildItem"},{"count":1,"class":"io.quarkus.arc.deployment.TransformedAnnotationsBuildItem"},{"count":1,"class":"io.quarkus.deployment.builditem.DevServicesLauncherConfigResultBuildItem"},{"count":1,"class":"io.quarkus.deployment.builditem.GeneratedFileSystemResourceHandledBuildItem"},{"count":1,"class":"io.quarkus.arc.deployment.AutoInjectAnnotationBuildItem"},{"count":1,"class":"io.quarkus.arc.deployment.CompletedApplicationClassPredicateBuildItem"},{"count":1,"class":"io.quarkus.deployment.pkg.builditem.OutputTargetBuildItem"},{"count":1,"class":"io.quarkus.deployment.builditem.ApplicationInfoBuildItem"},{"count":1,"class":"io.quarkus.deployment.ide.IdeRunningProcessBuildItem"},{"count":1,"class":"io.quarkus.deployment.ide.IdeFileBuildItem"},{"count":1,"class":"io.quarkus.deployment.builditem.MainClassBuildItem"},{"count":1,"class":"io.quarkus.deployment.logging.StaticInitLoggingSetupBuildItem"}],"itemsCount":503,"buildTarget":"quarkus-application"}